<!-- IBM_PROLOG_BEGIN_TAG                                                   -->
<!-- This is an automatically generated prolog.                             -->
<!--                                                                        -->
<!-- $Source: src/import/chips/p10/procedures/xml/error_info/p10_revert_sbe_mcs_setup_errors.xml $ -->
<!--                                                                        -->
<!-- OpenPOWER HostBoot Project                                             -->
<!--                                                                        -->
<!-- Contributors Listed Below - COPYRIGHT 2019,2020                        -->
<!-- [+] International Business Machines Corp.                              -->
<!--                                                                        -->
<!--                                                                        -->
<!-- Licensed under the Apache License, Version 2.0 (the "License");        -->
<!-- you may not use this file except in compliance with the License.       -->
<!-- You may obtain a copy of the License at                                -->
<!--                                                                        -->
<!--     http://www.apache.org/licenses/LICENSE-2.0                         -->
<!--                                                                        -->
<!-- Unless required by applicable law or agreed to in writing, software    -->
<!-- distributed under the License is distributed on an "AS IS" BASIS,      -->
<!-- WITHOUT WARRANTIES OR CONDITIONS OF ANY KIND, either express or        -->
<!-- implied. See the License for the specific language governing           -->
<!-- permissions and limitations under the License.                         -->
<!--                                                                        -->
<!-- IBM_PROLOG_END_TAG                                                     -->
<hwpErrors>
 <!-- ******************************************************************** -->
   <hwpError>
      <rc>RC_P10_REVERT_SBE_MCS_SETUP_NO_MI_TARGETS_FOUND</rc>
      <description>
        Procedure: p10_revert_sbe_mcs_setup
        No MI targets were found to revert.
      </description>
      <ffdc>CHIP</ffdc>
      <callout>
        <procedure>CODE</procedure>
        <priority>HIGH</priority>
      </callout>
   </hwpError>
 <!-- ******************************************************************** -->
   <hwpError>
      <rc>RC_P10_REVERT_SBE_MCS_SETUP_SELECTED_MC_NOT_FOUND</rc>
      <description>
        Procedure: p10_revert_sbe_mcs_setup
        The MC that was setup was not found and cannot be reverted
      </description>
      <ffdc>TARGET</ffdc>
      <ffdc>ATTR_PROC_SBE_MCS_SETUP_SELECTED_MC</ffdc>
      <callout>
        <procedure>CODE</procedure>
        <priority>HIGH</priority>
      </callout>
   </hwpError>
 <!-- ******************************************************************** -->
</hwpErrors>
