<!-- IBM_PROLOG_BEGIN_TAG                                                   -->
<!-- This is an automatically generated prolog.                             -->
<!--                                                                        -->
<!-- $Source: src/usr/hwpf/hwp/dram_training/mem_pll_setup/cen_mem_pll_initf_errors.xml $ -->
<!--                                                                        -->
<!-- IBM CONFIDENTIAL                                                       -->
<!--                                                                        -->
<!-- COPYRIGHT International Business Machines Corp. 2013                   -->
<!--                                                                        -->
<!-- p1                                                                     -->
<!--                                                                        -->
<!-- Object Code Only (OCO) source materials                                -->
<!-- Licensed Internal Code Source Materials                                -->
<!-- IBM HostBoot Licensed Internal Code                                    -->
<!--                                                                        -->
<!-- The source code for this program is not published or otherwise         -->
<!-- divested of its trade secrets, irrespective of what has been           -->
<!-- deposited with the U.S. Copyright Office.                              -->
<!--                                                                        -->
<!-- Origin: 30                                                             -->
<!--                                                                        -->
<!-- IBM_PROLOG_END_TAG                                                     -->
<!-- $Id: cen_mem_pll_initf_errors.xml,v 1.1 2013/11/15 16:30:43 mfred Exp $ -->
<!-- Error definitions for cen_mem_pll_initf -->
<hwpErrors>
  <!-- *********************************************************************** -->
  <hwpError>
    <rc>RC_CEN_MEM_PLL_INITF_UNSUPPORTED_MSS_FREQ</rc>
    <description>
        cen_mem_pll_initf found unsupported memory channel frequency in
        ATTR_MSS_FREQ attribute.
    </description>
    <ffdc>MSS_FREQ</ffdc>
    <callout>
      <procedure>CODE</procedure>
      <priority>HIGH</priority>
    </callout>
  </hwpError>
  <!-- *********************************************************************** -->
  <hwpError>
    <rc>RC_CEN_MEM_PLL_INITF_UNSUPPORTED_NEST_FREQ</rc>
    <description>
        cen_mem_pll_initf found unsupported nest frequency in
        ATTR_FREQ_PB attribute.
    </description>
    <ffdc>NEST_FREQ</ffdc>
    <callout>
      <procedure>CODE</procedure>
      <priority>HIGH</priority>
    </callout>
  </hwpError>
</hwpErrors>
